CHANGELOG.txt
LICENCE.txt
MANIFEST.in
README.txt
setup.py
dakshbasiccalculator.egg-info/SOURCES.txt
dakshbasiccalculator.egg-info/dependency_links.txt
dakshbasiccalculator.egg-info/top_level.txt
dakshbasicpackage/__init__.py
dakshbasicpackage.egg-info/PKG-INFO
dakshbasicpackage.egg-info/SOURCES.txt
dakshbasicpackage.egg-info/dependency_links.txt
dakshbasicpackage.egg-info/top_level.txt