Metadata-Version: 1.1
Name: dakshbasicpackage
Version: 0.0.1
Summary: Basic Print statement
Home-page: UNKNOWN
Author: Daksh Kanoria
Author-email: contact@dakshkanria.me
License: MIT
Keywords: print
Platform: UNKNOWN
Classifier: Development Status :: 5 - Production/Stable
Classifier: Intended Audience :: Education
Classifier: Operating System :: Microsoft :: Windows :: Windows 10
Classifier: License :: OSI Approved :: MIT License
Classifier: Programming Language :: Python :: 3
